web_live_data_fetcher/__init__.py
web_live_data_fetcher/google_search.py
web_live_data_fetcher/web_scraper.py
web_live_data_fetcher-0.1.1.dist-info/LICENSE
web_live_data_fetcher-0.1.1.dist-info/METADATA
web_live_data_fetcher-0.1.1.dist-info/WHEEL
web_live_data_fetcher-0.1.1.dist-info/top_level.txt
web_live_data_fetcher-0.1.1.dist-info/RECORD
